MANIFEST.in
README.rst
requirements.txt
setup.py
examples/config.cfg
examples/test_scripts/example_httplib.py
examples/test_scripts/example_mechanize_simple.py
examples/test_scripts/example_mechanize_wikipedia.py
examples/test_scripts/example_mock.py
examples/test_scripts/example_urllib2.py
pyak47/__init__.py
pyak47/core.py
pyak47/dependency_checker.py
pyak47/graph.py
pyak47/progressbar.py
pyak47/reportwriter.py
pyak47/reportwriterxml.py
pyak47/results.py
pyak47/resultsloader.py
pyak47/resultswriter.py
pyak47/rpcserver.py
pyak47/script_loader.py
pyak47.egg-info/PKG-INFO
pyak47.egg-info/SOURCES.txt
pyak47.egg-info/dependency_links.txt
pyak47.egg-info/entry_points.txt
pyak47.egg-info/requires.txt
pyak47.egg-info/top_level.txt
pyak47/utilities/__init__.py
pyak47/utilities/gridgui.py
pyak47/utilities/newproject.py
pyak47/utilities/run.py