Metadata-Version: 1.1
Name: pyak47
Version: 1.2.1
Summary: pyak47 - Performance Test Framework
Home-page: https://github.com/kakwa/pyak47/
Author: Pierre-Francois Carpentier
Author-email: carpentier.pf@gmail.com
License: UNKNOWN
Keywords: performance,scalability,load,test,testing,benchmark
Platform: UNKNOWN
Classifier: Development Status :: 4 - Beta
Classifier: License :: OSI Approved :: GNU Library or Lesser General Public License (LGPL)
Classifier: Operating System :: OS Independent
Classifier: Programming Language :: Python
Classifier: Programming Language :: Python :: 2.6
Classifier: Programming Language :: Python :: 2.7
Classifier: Topic :: Software Development :: Testing
Classifier: Topic :: Software Development :: Testing :: Traffic Generation
Classifier: Topic :: System :: Benchmark
